{"id":"19054","assetBundleId":"-1","components":[{"type":23,"id":"18820","data":[0.5,0.5,0,0,1,1,0,0,0,0,0,0,0,0,1,1,1,1]}],"children":[{"id":"21542","assetBundleId":"-1","components":[{"type":23,"id":"21540","data":[0.5,0.5,0.5,0.5,0.5,0.5,433,432,0,122,0,0,0,0,1,1,1,1]},{"type":24,"id":"21548","data":[0]},{"type":25,"id":"21550","enabled":1,"class":32,"data":[33,"18836",0,0,1,4,1,1,0,0,1,null,null,1,1,1,1,1,1]}],"children":[{"id":"21552","assetBundleId":"-1","components":[{"type":23,"id":"21544","data":[0.5,0,0.5,0,0.5,0,290,92,0,-146,0,0,0,0,1,1,1,1]},{"type":24,"id":"21570","data":[0]},{"type":25,"id":"21572","enabled":1,"class":32,"data":[33,"19158",0,0,1,4,1,1,0,0,1,null,null,1,1,1,1,1,1]},{"type":25,"id":"19032","enabled":1,"class":34,"data":[[[[]]],[3,null,null,null,null,null,null,null,null],1,[1,1,1,1,0.960784316062927,0.960784316062927,0.960784316062927,1,0.7843137383461,0.7843137383461,0.7843137383461,1,0.960784316062927,0.960784316062927,0.960784316062927,1,0.7843137383461,0.7843137383461,0.7843137383461,0.501960813999176,1,0.100000001490116],[null,null,null,null,null,null,null,null],["Normal","Highlighted","Pressed","Selected","Disabled"],1,32,"21572"]},{"type":25,"id":"21574","enabled":1,"class":35,"data":[1]}],"children":[{"id":"19050","assetBundleId":"-1","components":[{"type":23,"id":"19048","data":[0.5,0.5,0.5,0.5,0.5,0.5,19.9552307128906,100,-40.0200004577637,0,0,0,0,-0.171241387724876,0.985229134559631,1,1,1]},{"type":24,"id":"21576","data":[0]},{"type":25,"id":"21578","enabled":1,"class":32,"data":[null,null,0,0,1,4,1,1,0,0,1,null,null,1,0.926007151603699,1,0.316037714481354,0.615686297416687,1]}],"children":[],"data":["Image","Untagged",1,0,5]},{"id":"21564","assetBundleId":"-1","components":[{"type":23,"id":"21554","data":[0.5,0.5,0,0.5,0,0.5,286,92,140.600006103516,0,0,0,0,0,1,1,1,1]},{"type":24,"id":"21586","data":[0]},{"type":25,"id":"21588","enabled":1,"class":36,"data":[0,null,null,0,0,0,0,"PLAY",0,27,"18892",5,"18894",[],null,null,[],255,255,255,255,1,1,1,1,0,3,[1,1,1,1,1,1,1,1,1,1,1,1,1,1,1,1],null,null,null,null,0,null,null,-1183493901,0,255,255,255,255,48,48,400,0,18,72,1,2,512,65535,0,0,0,0,0,0,1,0.400000005960464,0,null,null,null,null,1,0,0,1,1,1,0,0,0,0,0,0,1,1,1,0,0,0,0,0,0,null,null,1,1,1,1,1,1]}],"children":[],"data":["Text (TMP)","Untagged",1,0,5]},{"id":"21566","assetBundleId":"-1","components":[{"type":23,"id":"21556","data":[0.5,0.5,1,0.5,1,0.5,70,70,-52,0,0,0,0,0,1,1,1,1]},{"type":24,"id":"21582","data":[0]},{"type":25,"id":"21584","enabled":1,"class":32,"data":[33,"21590",0,1,1,4,1,1,0,0,1,null,null,1,1,1,1,1,1]}],"children":[{"id":"21580","assetBundleId":"-1","components":[{"type":23,"id":"21568","data":[0.5,0.5,0,0,1,1,0,0,0,0,0,0,0,0,1,1,1,1]},{"type":24,"id":"21592","data":[0]},{"type":25,"id":"21594","enabled":1,"class":36,"data":[0,null,null,0,0,0,0,"1",0,27,"21596",5,"21598",[],null,null,[],255,255,255,255,1,1,1,1,0,3,[1,1,1,1,1,1,1,1,1,1,1,1,1,1,1,1],null,null,null,null,0,null,null,0,0,255,255,255,255,40,40,400,0,18,72,1,2,512,65535,0,0,0,0,0,0,1,0.400000005960464,0,null,null,null,null,1,0,0,1,1,1,0,0,0,0,0,0,1,1,1,0,0,0,0,0,0,null,null,1,1,1,1,1,1]}],"children":[],"data":["Text (TMP)","Untagged",1,0,5]}],"data":["energy","Untagged",0,0,5]}],"data":["btnPlay_snipeMode","Untagged",1,0,5]},{"id":"18864","assetBundleId":"-1","components":[{"type":23,"id":"19052","data":[0.5,0.5,0,0,1,1,-11.1376953125,-124.745574951172,-0.100006103515625,-17.6000061035156,0,0,0,0,1,1,1,1]},{"type":24,"id":"21562","data":[0]},{"type":25,"id":"19120","enabled":1,"class":32,"data":[null,null,0,1,1,4,1,1,0,0,1,null,null,1,1,1,1,1,1]},{"type":25,"id":"18908","enabled":1,"class":34,"data":[[[[]]],[3,null,null,null,null,null,null,null,null],1,[1,1,1,1,0.960784316062927,0.960784316062927,0.960784316062927,1,0.7843137383461,0.7843137383461,0.7843137383461,1,0.960784316062927,0.960784316062927,0.960784316062927,1,0.7843137383461,0.7843137383461,0.7843137383461,0.501960813999176,1,0.100000001490116],[null,null,null,null,null,null,null,null],["Normal","Highlighted","Pressed","Selected","Disabled"],1,32,"19120"]}],"children":[],"data":["ButtonSW","Untagged",1,0,5]},{"id":"21558","assetBundleId":"-1","components":[{"type":23,"id":"21546","data":[0.5,1,0,1,1,1,0,50,0,-15,0,0,0,0,1,1,1,1]},{"type":24,"id":"21560","data":[0]},{"type":25,"id":"19198","enabled":1,"class":36,"data":[0,null,null,0,0,0,0,"SUNSHINE KINGDOM",0,27,"19834",5,"20062",[],null,null,[],255,255,255,255,1,1,1,1,0,3,[1,1,1,1,1,1,1,1,1,1,1,1,1,1,1,1],null,null,null,null,0,null,null,-1183493901,0,255,255,255,255,36,36,400,0,18,72,1,2,1024,65535,0,0,0,0,0,0,1,0.400000005960464,0,null,null,null,null,1,0,0,1,1,1,0,0,0,0,0,0,1,1,1,0,0,0,0,0,0,null,null,1,1,1,1,1,1]}],"children":[],"data":["txtWorldNameText","Untagged",1,0,5]}],"data":["bgWorldPanel","Untagged",1,0,5]}],"data":["PanelWorldHome","Untagged",1,0,5]}